{
  "_fv": 34,
  "_type": "recipe",
  "definition": {
    "recipeType": "Crafting",
    "xpReward": 0.0,
    "cookingTime": 200,
    "recipeRetstackSize": 1,
    "group": "",
    "recipeShapeless": false,
    "recipeSlots": [
      {
        "value": "Blocks.WOOL#14"
      },
      {
        "value": "Blocks.WOOL#14"
      },
      {
        "value": "Blocks.WOOL#14"
      },
      {
        "value": "Blocks.RED_FLOWER#2"
      },
      {
        "value": "Blocks.WOOL#14"
      },
      {
        "value": "Blocks.RED_FLOWER#2"
      },
      {
        "value": "Blocks.PLANKS"
      },
      {
        "value": ""
      },
      {
        "value": "Blocks.PLANKS"
      }
    ],
    "recipeReturnStack": {
      "value": "CUSTOM:LuphieFuschiaArmchair"
    },
    "name": "luphie_fuschia_armchair_recipe",
    "namespace": "mod"
  }
}